odoo/addons/sale_merge_draft_invoice/README.rst
odoo/addons/sale_merge_draft_invoice/__init__.py
odoo/addons/sale_merge_draft_invoice/__manifest__.py
odoo/addons/sale_merge_draft_invoice/model/__init__.py
odoo/addons/sale_merge_draft_invoice/model/res_company.py
odoo/addons/sale_merge_draft_invoice/model/res_config_settings.py
odoo/addons/sale_merge_draft_invoice/model/sale_order.py
odoo/addons/sale_merge_draft_invoice/security/sale_merge_draft_invoice_security.xml
odoo/addons/sale_merge_draft_invoice/static/description/icon.png
odoo/addons/sale_merge_draft_invoice/tests/__init__.py
odoo/addons/sale_merge_draft_invoice/tests/test_sale_merge_draft_invoice.py
odoo/addons/sale_merge_draft_invoice/view/res_config_settings_views.xml
odoo/addons/sale_merge_draft_invoice/wizard/__init__.py
odoo/addons/sale_merge_draft_invoice/wizard/sale_make_invoice_advance.py
odoo/addons/sale_merge_draft_invoice/wizard/sale_make_invoice_advance_views.xml
odoo11_addon_sale_merge_draft_invoice-11.0.1.0.0.dist-info/DESCRIPTION.rst
odoo11_addon_sale_merge_draft_invoice-11.0.1.0.0.dist-info/METADATA
odoo11_addon_sale_merge_draft_invoice-11.0.1.0.0.dist-info/RECORD
odoo11_addon_sale_merge_draft_invoice-11.0.1.0.0.dist-info/WHEEL
odoo11_addon_sale_merge_draft_invoice-11.0.1.0.0.dist-info/metadata.json
odoo11_addon_sale_merge_draft_invoice-11.0.1.0.0.dist-info/top_level.txt
